pymws/__init__.py
pymws/cli.py
pymws/exceptions.py
pymws/feeds.py
pymws/orders.py
pymws/products.py
pymws/pymws.py
pymws/reports.py
pymws/utils.py
pymws/fulfillment/__init__.py
pymws/fulfillment/inbound_shipment.py
pymws/fulfillment/outbound_shipment.py
pymws-0.2.0.dist-info/AUTHORS.rst
pymws-0.2.0.dist-info/LICENSE
pymws-0.2.0.dist-info/METADATA
pymws-0.2.0.dist-info/WHEEL
pymws-0.2.0.dist-info/entry_points.txt
pymws-0.2.0.dist-info/top_level.txt
pymws-0.2.0.dist-info/RECORD
