Metadata-Version: 2.1
Name: pymws
Version: 0.2.0
Summary: Python client for Amazon Marketplace Web Services (MWS)
Home-page: https://github.com/fulfilio/pymws
Author: Fulfil.IO Inc.
Author-email: help@fulfil.io
License: MIT license
Keywords: pymws
Platform: UNKNOWN
Classifier: Development Status :: 4 - Beta
Classifier: Intended Audience :: Developers
Classifier: License :: OSI Approved :: MIT License
Classifier: Natural Language :: English
Classifier: Programming Language :: Python :: 3
Classifier: Programming Language :: Python :: 3.5
Classifier: Programming Language :: Python :: 3.6
Classifier: Programming Language :: Python :: 3.7
Classifier: Programming Language :: Python :: 3.8
Requires-Python: >=3.5
Requires-Dist: Click (>=7.0)
Requires-Dist: lxml
Requires-Dist: requests
